disv.py
diserver-1.0.0.dist-info/LICENSE
diserver-1.0.0.dist-info/METADATA
diserver-1.0.0.dist-info/WHEEL
diserver-1.0.0.dist-info/entry_points.txt
diserver-1.0.0.dist-info/top_level.txt
diserver-1.0.0.dist-info/RECORD
